{"category_name":"medium","status":"success","problem_code":"CNPIIM","problem_name":"Counting Matrices","body":"<span class=\"solution-visible-txt\">All submissions for this problem are available.<\/span><h3> Read problems statements in <a target=\"_blank\" href=\"http:\/\/www.codechef.com\/download\/translated\/APRIL14\/mandarin\/CNPIIM.pdf\">Mandarin Chinese <\/a> and <a target=\"_blank\" href=\"http:\/\/www.codechef.com\/download\/translated\/APRIL14\/russian\/CNPIIM.pdf\">Russian<\/a>.<\/h3>\n<p>\u00a0<\/p>\n<p>Lira loves Linear Algebra and she is especially keen about matrix :).<\/p>\n<p>Today, she learnt some properties about matrices, namely, she learnt about what the trace of a matrix is, as her teacher gave her many exercises for her to practice.<\/p>\n<p>As we know she is pretty clever, she rapidly came up with some definitions of her own and devised a somewhat harder version of the problem initially proposed by her teacher.\n<\/p><p>Namely, she defines a <b>Positive Invertible Integer Matrix<\/b> as being an invertible 2x2 matrix composed only of positive (i.e. greater than 0) integer elements and whose determinant is greater than 0.<\/p>\n<p>Now, she is interested in counting how many such matrices are there, such that their trace is equal to <b>N<\/b> .<\/p>\n<p>It's your turn to solve Lira's problem :D<\/p>\n<h3>Input<\/h3>\n<p>The first line of the input contains an integer <b>T<\/b> denoting the number of test cases. The description of <b>T<\/b> test cases follows. <br \/><br \/>\nEach test case consist of single integer <b>N<\/b>, the trace of the matrix.\n<\/p>\n\n<h3>Output<\/h3>\n<p>For each test case, output a single line containing the number of <b>Positive Invertible Integer Matrices<\/b> such that their trace is equal to <b>N<\/b> and determinant is positive.<\/p>\n<p>Read here for additional info:<\/p>\n<p><a href=\"http:\/\/en.wikipedia.org\/wiki\/Trace_(linear_algebra)\">http:\/\/en.wikipedia.org\/wiki\/Trace_(linear_algebra)<\/a><\/p>\n<p><a href=\"http:\/\/en.wikipedia.org\/wiki\/Determinant\">http:\/\/en.wikipedia.org\/wiki\/Determinant<\/a> <\/p>\n<h3>Constraints:<\/h3>\n<ul>\n<li><b>1<\/b> \u2264 <b>T<\/b> \u2264 <b>50<\/b><\/li>\n<li><b>3<\/b> \u2264 <b>N<\/b> \u2264 <b>2500<\/b><\/li>\n<\/ul>\n<p>\u00a0<\/p>\n<h3>Example<\/h3>\n<pre><b>Input:<\/b>\n1\n3\n\n<b>Output:<\/b>\n2\t\n<\/pre><h3>Explanation<\/h3>\n<p>The only two matrices that exist with trace equal to 3 and that satisfy all the given conditions are:<\/p>\n<p><img src=\"\/download\/extimages\/0a3c6a4adf4feefa0ff7eb3765ac8959.gif\" alt=\"Matrices\" width=\"91\" height=\"42\" \/><\/p>\n","languages_supported":"ADA, ASM, BASH, BF, C, C99 strict, CAML, CLOJ, CLPS, CPP 4.3.2, CPP 4.9.2, CPP14, CS2, D, ERL, FORT, FS, GO, HASK, ICK, ICON, JAVA, JS, LISP clisp, LISP sbcl, LUA, NEM, NICE, NODEJS, PAS fpc, PAS gpc, PERL, PERL6, PHP, PIKE, PRLG, PYTH, PYTH 3.4, RUBY, SCALA, SCM guile, SCM qobi, ST, TCL, TEXT, WSPC","max_timelimit":"2","source_sizelimit":"50000","problem_author":"kuruma","problem_author_html_handle":"<span \n            class='rating' \n            style='display: inline-block; \n                    font-size: 10px; \n                    background: #1E7D22;\n                    padding: 0 3px; \n                    line-height: 1.3; \n                    color: white;\n                    margin-right: 2px;'>2&#9733;<\/span><span>kuruma<\/span>","problem_tester":"shiplu","problem_tester_html_handle":"<span \n            class='rating' \n            style='display: inline-block; \n                    font-size: 10px; \n                    background: #1E7D22;\n                    padding: 0 3px; \n                    line-height: 1.3; \n                    color: white;\n                    margin-right: 2px;'>2&#9733;<\/span><span>shiplu<\/span>","date_added":"2-12-2013","tags":"<a class='problem-tag-small ' href='\/tags\/problems\/april14'>\n                    april14\n                <\/a><a class='problem-tag-small ' href='\/tags\/problems\/easy-medium'>\n                    easy-medium\n                <\/a><a class='problem-tag-small ' href='\/tags\/problems\/kuruma'>\n                    kuruma\n                <\/a><a class='problem-tag-small ' href='\/tags\/problems\/maths'>\n                    maths\n                <\/a>","editorial_url":"http:\/\/discuss.codechef.com\/problems\/CNPIIM","user":{"username":null},"time":{"view_start_date":1397468002,"submit_start_date":1397468002,"visible_start_date":1397467741,"end_date":1735669800,"current":1493557588},"todo":false,"problem_status":"unattempted"}