{"category_name":"school","status":"success","problem_code":"MXZERO","problem_name":"Make XOR zero","body":"<span class=\"solution-visible-txt\">All submissions for this problem are available.<\/span><h3> Read problems statements in <a target=\"_blank\" href=\"http:\/\/www.codechef.com\/download\/translated\/SNCK151B\/mandarin\/MXZERO.pdf\">Mandarin Chinese <\/a> , <a target=\"_blank\" href=\"http:\/\/www.codechef.com\/download\/translated\/SNCK151B\/russian\/MXZERO.pdf\">Russian<\/a> and <a target=\"_blank\" href=\"http:\/\/www.codechef.com\/download\/translated\/SNCK151B\/vietnamese\/MXZERO.pdf\">Vietnamese<\/a><\/h3>\n\n\n<p>Olya has written <b>N<\/b> binary integers (i.e. either zero or one) on a blackboard. She recently learned about XOR operation. Now she wants to erase exactly one integer in the array so that the <a href=\"http:\/\/en.wikipedia.org\/wiki\/Exclusive_or\">XOR<\/a> of the remaining <b>N - 1<\/b> numbers is zero. Please help her to calculate the number of ways of doing so.<\/p>\n\n<h3>Input<\/h3>\n<p>The first line of the input contains an integer <b>T<\/b> denoting the number of test cases. The description of <b>T<\/b> test cases follows.<\/p>\n<p>The first line of each test case contains a single integer <b>N<\/b> denoting the number of numbers that Olya has written on a blackboard.<\/p> \n<p>The second line contains <b>N<\/b> space-separated integers <b>A<sub>1<\/sub><\/b>, <b>A<sub>2<\/sub><\/b>, ..., <b>A<sub>N<\/sub><\/b> denoting the numbers she had written. <\/p>\n\n<h3>Output<\/h3>\nFor each test case, output a single line containing the number of ways to erase exactly one integer so that the XOR of the remaining integers is zero. The ways where you erase the same integer but on different places in the given sequence are considered different.\n\n<h3>Constraints<\/h3>\n<ul>\n<li><b>1<\/b> \u2264 <b>T<\/b> \u2264 <b>20<\/b><\/li>\n<li><b>2<\/b> \u2264 <b>N<\/b> \u2264 <b>10<sup>5<\/sup><\/b><\/li>\n<li><b>0<\/b> \u2264 <b>A<sub>i<\/sub><\/b> \u2264 <b>1<\/b><\/li>\n<\/ul>\n\n<h3>Example<\/h3>\n<pre><b>Input:<\/b>\n2\n5\n1 0 0 0 0\n5\n1 1 1 1 1\n\n<b>Output:<\/b>\n1\n5\n<\/pre>\n\n<h3>Explanation<\/h3>\n<p><b>Example case 1.<\/b> If you erase the first number on the blackboard, then the XOR of the rest of numbers will be equal to zero.<\/p>\n<p><b>Example case 2.<\/b> You can erase any of the given 5 numbers, it will make the XOR of the rest equal to zero.<\/p>","languages_supported":"ADA, ASM, BASH, BF, C, C99 strict, CAML, CLOJ, CLPS, CPP 4.3.2, CPP 4.9.2, CPP14, CS2, D, ERL, FORT, FS, GO, HASK, ICK, ICON, JAVA, JS, LISP clisp, LISP sbcl, LUA, NEM, NICE, NODEJS, PAS fpc, PAS gpc, PERL, PERL6, PHP, PIKE, PRLG, PYPY, PYTH, PYTH 3.4, RUBY, SCALA, SCM chicken, SCM guile, SCM qobi, ST, TCL, TEXT, WSPC","max_timelimit":"1","source_sizelimit":"50000","problem_author":"xcwgf666","problem_author_html_handle":"<span \n            class='rating' \n            style='display: inline-block; \n                    font-size: 10px; \n                    background: #FF7F00;\n                    padding: 0 3px; \n                    line-height: 1.3; \n                    color: white;\n                    margin-right: 2px;'>6&#9733;<\/span><span>xcwgf666<\/span>","problem_tester":null,"problem_tester_html_handle":"","date_added":"13-05-2015","tags":"<a class='problem-tag-small ' href='\/tags\/problems\/ad-hoc'>\n                    ad-hoc\n                <\/a><a class='problem-tag-small ' href='\/tags\/problems\/counting'>\n                    counting\n                <\/a><a class='problem-tag-small ' href='\/tags\/problems\/snck151b'>\n                    snck151b\n                <\/a><a class='problem-tag-small ' href='\/tags\/problems\/xcwgf666'>\n                    xcwgf666\n                <\/a>","editorial_url":"http:\/\/discuss.codechef.com\/problems\/MXZERO","user":{"username":null},"time":{"view_start_date":1432954800,"submit_start_date":1432954800,"visible_start_date":1432954800,"end_date":1735669800,"current":1492506751},"todo":false,"problem_status":"unattempted"}