{"category_name":"easy","status":"success","problem_code":"CIELTOMY","problem_name":"Ciel and Tomya","body":"<span class=\"solution-visible-txt\">All submissions for this problem are available.<\/span><p>\nTomya is a girl. She loves Chef Ciel very much.\n<\/p>\n\n<p>\nToday, too, Tomya is going to Ciel's restaurant.\nOf course, Tomya would like to go to Ciel's restaurant as soon as possible.\nTherefore Tomya uses one of the shortest paths from Tomya's house to Ciel's restaurant.\nOn the other hand, Tomya is boring now to use the same path many times.\nSo Tomya wants to know the number of shortest paths from Tomya's house to Ciel's restaurant.\nYour task is to calculate the number under the following assumptions.\n<\/p>\n\n<p>\nThis town has <b>N<\/b> intersections and <b>M<\/b> two way roads.\nThe <b>i<\/b>-th road connects from the <b>A<sub>i<\/sub><\/b>-th intersection to the <b>B<sub>i<\/sub><\/b>-th intersection, and its length is \n\n<b>C<sub>i<\/sub><\/b>.\nTomya's house is in the 1st intersection, and Ciel's restaurant is in the <b>N<\/b>-th intersection.\n<\/p>\n\n\n<h3>Input<\/h3>\n<p>\nThe first line contains an integer <strong>T<\/strong>, the number of test cases.\nThen <strong>T<\/strong> test cases follow.\nThe first line of each test case contains 2 integers <b>N<\/b>, <b>M<\/b>.\nThen next <b>M<\/b> lines contains 3 integers denoting <b>A<sub>i<\/sub><\/b>, <b>B<sub>i<\/sub><\/b> and <b>C<sub>i<\/sub><\/b>.\n<\/p>\n\n<h3>Output<\/h3>\n<p>\nFor each test case, print the number of shortest paths from Tomya's house to Ciel's restaurant.\n<\/p>\n\n<h3>Constraints<\/h3>\n<p>\n1 \u2264 <b>T<\/b> \u2264 10<br \/>\n2 \u2264 <b>N<\/b> \u2264 10<br \/>\n1 \u2264 <b>M<\/b> \u2264 <b>N \u2219 (N \u2013 1) \/ 2<\/b><br \/>\n1 \u2264 <b>A<sub>i<\/sub><\/b>, <b>B<sub>i<\/sub><\/b> \u2264 <b>N<\/b><br \/>\n1 \u2264 <b>C<sub>i<\/sub><\/b> \u2264 10<br \/>\n<b>A<sub>i<\/sub><\/b> \u2260 <b>B<sub>i<\/sub><\/b><br \/>\nIf <b>i<\/b> \u2260 <b>j<\/b> and <b>A<sub>i<\/sub><\/b> = <b>A<sub>j<\/sub><\/b>, then <b>B<sub>i<\/sub><\/b> \u2260 <b>B<sub>j<\/sub><\/b><br \/>\nThere is at least one path from Tomya's house to Ciel's restaurant.<br \/>\n<\/p>\n\n<h3>Sample Input<\/h3>\n<pre>2\n3 3\n1 2 3\n2 3 6\n1 3 7\n3 3\n1 2 3\n2 3 6\n1 3 9<\/pre>\n\n<h3>Sample Output<\/h3>\n<pre>1\n2<\/pre>\n\n<h3>Explanations<\/h3>\n\n<p>\nIn the first sample, only one shortest path exists, which is 1-3.\n<\/p>\n<p>\nIn the second sample, both paths 1-2-3 and 1-3 are the shortest paths.\n<\/p>","languages_supported":"ADA, ASM, BASH, BF, C, C99 strict, CAML, CLOJ, CLPS, CPP 4.3.2, CPP 4.9.2, CPP14, CS2, D, ERL, FORT, FS, GO, HASK, ICK, ICON, JAVA, JS, LISP clisp, LISP sbcl, LUA, NEM, NICE, NODEJS, PAS fpc, PAS gpc, PERL, PERL6, PHP, PIKE, PRLG, PYTH, PYTH 3.4, RUBY, SCALA, SCM guile, SCM qobi, ST, TCL, TEXT, WSPC","max_timelimit":"2","source_sizelimit":"50000","problem_author":"laycurse","problem_author_html_handle":"<span \n            class='rating' \n            style='display: inline-block; \n                    font-size: 10px; \n                    background: #FF7F00;\n                    padding: 0 3px; \n                    line-height: 1.3; \n                    color: white;\n                    margin-right: 2px;'>6&#9733;<\/span><span>laycurse<\/span>","problem_tester":null,"problem_tester_html_handle":"","date_added":"4-07-2012","tags":"<a class='problem-tag-small ' href='\/tags\/problems\/backtracking'>\n                    backtracking\n                <\/a><a class='problem-tag-small ' href='\/tags\/problems\/cook24'>\n                    cook24\n                <\/a><a class='problem-tag-small ' href='\/tags\/problems\/laycurse'>\n                    laycurse\n                <\/a><a class='problem-tag-small ' href='\/tags\/problems\/simple'>\n                    simple\n                <\/a>","editorial_url":"http:\/\/discuss.codechef.com\/problems\/CIELTOMY","user":{"username":null},"time":{"view_start_date":1342982953,"submit_start_date":1342982953,"visible_start_date":1342982428,"end_date":1735669800,"current":1493558130},"todo":false,"problem_status":"unattempted"}