{"category_name":"hard","status":"success","problem_code":"ASTRD","problem_name":"Asteroids","body":"<span class=\"solution-visible-txt\">All submissions for this problem are available.<\/span><h3> Read problems statements in <a target=\"_blank\" href=\"http:\/\/www.codechef.com\/download\/translated\/JAN16\/mandarin\/ASTRD.pdf\">Mandarin Chinese<\/a>, <a target=\"_blank\" href=\"http:\/\/www.codechef.com\/download\/translated\/JAN16\/russian\/ASTRD.pdf\">Russian<\/a> and <a target=\"_blank\" href=\"http:\/\/www.codechef.com\/download\/translated\/JAN16\/vietnamese\/ASTRD.pdf\">Vietnamese<\/a> as well.<\/h3>\n\n\n<p>Your planet is a perfect sphere with radius <b>R<\/b> and center at <b>(0, 0, 0)<\/b>. There are <b>N<\/b> asteroids around the planet. Your task is to find the <b>minimal<\/b> possible number of asteroids you can observe from some point on the suface of the planet. An asteroid can be observed if it's at least <b>10<sup>-3<\/sup><\/b> above the horizon line at the place of the observation.<\/p>\n\n<h3>Input<\/h3>\n<p>The first line of input contains a single integer <b>T<\/b>, denoting the number of testcases.<\/p>\n<p>The first line of each test case contains two space-separated integers, <b>N<\/b> and <b>R<\/b>.<\/p>\n<p>The following <b>N<\/b> lines contains 3 space-separated integers each: coordinates <b>x<sub>i<\/sub>, y<sub>i<\/sub>, z<sub>i<\/sub><\/b> of the corresponding asteroid. <\/p>\n\n<h3>Output<\/h3>\n<p>For each test case, output one integer in a new line: the answer for the test case.<\/p>\n\n<h3>Constraints<\/h3>\n<ul>\n<li><b>1<\/b> \u2264 <b>T<\/b> \u2264 <b>10<\/b><\/li>\n<li><b>1<\/b> \u2264 <b>R<\/b> \u2264 <b>10<\/b><\/li>\n<li><b>R - 1<\/b> \u2264 <b>|x<sub>i<\/sub>|, |y<sub>i<\/sub>|, |z<sub>i<\/sub>|<\/b> \u2264 <b>50<\/b><\/li>\n<li><b>Subtask 1[11 points]: <\/b><b>1<\/b> \u2264 <b>N<\/b> \u2264 <b>2<\/b><\/li>\n<li><b>Subtask 2[89 points]: <\/b><b>1<\/b> \u2264 <b>N<\/b> \u2264 <b>150<\/b><\/li>\n<\/ul>\n\n<h3>Example<\/h3>\n<pre><b>Input:<\/b>\n1\n3 1\n2 2 2\n0 3 4\n4 5 0\n\n<b>Output:<\/b>\n0\n<\/pre>\n\n<h3>Sample explanation:<\/h3>\nOne of the solutions can be: as all the asteroids have positive coordinates, we can choose some point on the surface which lies in the all-negative octant (see octant VII <a href='https:\/\/en.wikipedia.org\/wiki\/Octant_%28solid_geometry%29'>here<\/a>), and none of the asteroids will be observed.\n","languages_supported":"ADA, ASM, BASH, BF, C, C99 strict, CAML, CLOJ, CLPS, CPP 4.3.2, CPP 4.9.2, CPP14, CS2, D, ERL, FORT, FS, GO, HASK, ICK, ICON, JAVA, JS, LISP clisp, LISP sbcl, LUA, NEM, NICE, NODEJS, PAS fpc, PAS gpc, PERL, PERL6, PHP, PIKE, PRLG, PYPY, PYTH, PYTH 3.4, RUBY, SCALA, SCM chicken, SCM guile, SCM qobi, ST, TCL, TEXT, WSPC","max_timelimit":"1","source_sizelimit":"50000","problem_author":"pavel1996","problem_author_html_handle":"<span \n            class='rating' \n            style='display: inline-block; \n                    font-size: 10px; \n                    background: #684273;\n                    padding: 0 3px; \n                    line-height: 1.3; \n                    color: white;\n                    margin-right: 2px;'>4&#9733;<\/span><span>pavel1996<\/span>","problem_tester":"mgch","problem_tester_html_handle":"<span \n            class='rating' \n            style='display: inline-block; \n                    font-size: 10px; \n                    background: #D0011B;\n                    padding: 0 3px; \n                    line-height: 1.3; \n                    color: white;\n                    margin-right: 2px;'>7&#9733;<\/span><span>mgch<\/span>","date_added":"15-09-2015","tags":"<a class='problem-tag-small ' href='\/tags\/problems\/geometry'>\n                    geometry\n                <\/a><a class='problem-tag-small ' href='\/tags\/problems\/hard'>\n                    hard\n                <\/a><a class='problem-tag-small ' href='\/tags\/problems\/jan16'>\n                    jan16\n                <\/a><a class='problem-tag-small ' href='\/tags\/problems\/pavel1996'>\n                    pavel1996\n                <\/a>","editorial_url":"http:\/\/discuss.codechef.com\/problems\/ASTRD","user":{"username":null},"time":{"view_start_date":1452504600,"submit_start_date":1452504600,"visible_start_date":1452504600,"end_date":1735669800,"current":1493556613},"todo":false,"problem_status":"unattempted"}